[{"hito_id": "A1", "fecha": 2055.0, "keywords": "", "hito_texto": "Se tienen centros urbanos sustentables y resilientes", "hito_precedente": [], "subdimension": [], "subdisciplina": ["2.6"], "pregunta": "1", "dimension": [], "hito_consecuencia": ["A15"], "disciplinas": ["2"]}, {"hito_id": "A10", "fecha": 2020, "keywords": "", "hito_texto": "Se debe financiar públicamente proyectos de investigación multidisciplinarios y con productos heterogeneos", "hito_precedente": ["A18", "A19", "A20"], "subdimension": [], "subdisciplina": ["2.1"], "pregunta": "2", "dimension": [], "hito_consecuencia": [], "disciplinas": ["2"]}, {"hito_id": "A11", "fecha": 2025, "keywords": "", "hito_texto": "Se debe determinar el uso actual del recurso hídrico", "hito_precedente": ["A20"], "subdimension": ["rh.3", "rh.4"], "subdisciplina": ["1.1"], "pregunta": "4", "dimension": ["rh"], "hito_consecuencia": [], "disciplinas": ["1"]}, {"hito_id": "A12", "fecha": 2035, "keywords": "", "hito_texto": "Disminuye la huella hídrica", "hito_precedente": ["A4"], "subdimension": ["rh.2", "rh.3"], "subdisciplina": ["1.1"], "pregunta": "", "dimension": ["rh"], "hito_consecuencia": [], "disciplinas": ["1"]}, {"hito_id": "A13", "fecha": 2040, "keywords": "", "hito_texto": "Aumenta el numero de investigadores y se establecen masas críticas", "hito_precedente": ["A5"], "subdimension": [], "subdisciplina": ["2.1"], "pregunta": "", "dimension": [], "hito_consecuencia": [], "disciplinas": ["2"]}, {"hito_id": "A14", "fecha": 2045, "keywords": "", "hito_texto": "Se datifica la toma de decisiones", "hito_precedente": ["A3", "A2"], "subdimension": [], "subdisciplina": ["2.4"], "pregunta": "", "dimension": [], "hito_consecuencia": [], "disciplinas": ["2"]}, {"hito_id": "A15", "fecha": 2050, "keywords": "", "hito_texto": "Se debe mejorar la planificación de uso del territorio sumergido", "hito_precedente": ["A1", "A2"], "subdimension": [], "subdisciplina": ["3.1"], "pregunta": "", "dimension": [], "hito_consecuencia": [], "disciplinas": ["3"]}, {"hito_id": "A16", "fecha": 2035, "keywords": "", "hito_texto": "Hay planificación informada y una nueva ley de pesca", "hito_precedente": ["A6"], "subdimension": [], "subdisciplina": ["2.4"], "pregunta": "", "dimension": ["rh"], "hito_consecuencia": [], "disciplinas": ["2"]}, {"hito_id": "A18", "fecha": -1, "keywords": "", "hito_texto": "Se debe permitir el crecimiento del número de investigadores mediante puestos en centros", "hito_precedente": [], "subdimension": ["rh.1", "rh.3"], "subdisciplina": ["2.1"], "pregunta": "", "dimension": [], "hito_consecuencia": ["A10"], "disciplinas": ["2"]}, {"hito_id": "A19", "fecha": 2018, "keywords": "", "hito_texto": "Se deben flexibilizar los criterios con los que se evalúa el desempeño", "hito_precedente": [], "subdimension": [], "subdisciplina": ["3.1"], "pregunta": "", "dimension": [], "hito_consecuencia": ["A10"], "disciplinas": ["3"]}, {"hito_id": "A2", "fecha": 2035, "keywords": "", "hito_texto": "Se debe implementar modelos oceanográficos y biogeoquímicos operacionales que asimilen en tiempo cuasi real la información generada por la red de monitoreo", "hito_precedente": [], "subdimension": ["rh.4", "rh.5"], "subdisciplina": ["1.3"], "pregunta": "3", "dimension": ["rh"], "hito_consecuencia": ["A14", "A15"], "disciplinas": ["1"]}, {"hito_id": "A20", "fecha": 2018, "keywords": "", "hito_texto": "Se debe generar un Ministerio de Ciencias y Tecnologías con recursos para financiar un programa de observación", "hito_precedente": [], "subdimension": [], "subdisciplina": ["2.3"], "pregunta": "", "dimension": [], "hito_consecuencia": ["A8", "A9", "A10", "A11"], "disciplinas": ["2"]}, {"hito_id": "A21", "fecha": 2018, "keywords": "", "hito_texto": "Se replantea el rol y el funcionamiento de las agencias actualmente involucradas", "hito_precedente": [], "subdimension": [], "subdisciplina": ["2.3"], "pregunta": "", "dimension": [], "hito_consecuencia": ["A8", "A9"], "disciplinas": ["2"]}, {"hito_id": "A22", "fecha": 2025, "keywords": "", "hito_texto": "Existe empoderamiento cudadano", "hito_precedente": [], "subdimension": [], "subdisciplina": ["2.5"], "pregunta": "", "dimension": [], "hito_consecuencia": ["A7"], "disciplinas": ["2"]}, {"hito_id": "A23", "fecha": 2018, "keywords": "", "hito_texto": "Hay responsabilización ciudadana", "hito_precedente": [], "subdimension": [], "subdisciplina": ["2.5"], "pregunta": "", "dimension": [], "hito_consecuencia": ["A8"], "disciplinas": ["2"]}, {"hito_id": "A3", "fecha": 2040, "keywords": "", "hito_texto": "Se debe establecer y desarrollar criterios de modelos óptimos de recursos hídricos con valores ambientales, sociales y económicos sustentables", "hito_precedente": [], "subdimension": ["rh.4", "rh.2"], "subdisciplina": ["3.1"], "pregunta": "4", "dimension": ["rh"], "hito_consecuencia": ["A14"], "disciplinas": ["3"]}, {"hito_id": "A4", "fecha": 2030, "keywords": "", "hito_texto": "Se deben desarrollar modelos integrales validados", "hito_precedente": [], "subdimension": [], "subdisciplina": ["1.3"], "pregunta": "4", "dimension": [], "hito_consecuencia": ["A12"], "disciplinas": ["1"]}, {"hito_id": "A5", "fecha": 2030, "keywords": "", "hito_texto": "Se debe generar una institucionalidad estable para la investigación y acción en temas ambientales", "hito_precedente": [], "subdimension": [], "subdisciplina": ["2.3"], "pregunta": "2", "dimension": [], "hito_consecuencia": ["A13"], "disciplinas": ["2"]}, {"hito_id": "A6", "fecha": 2030, "keywords": "", "hito_texto": "Existe una red con adecuada resolución espacial de monitoreo oceanográfico y sistema de transmisión, acopio y distribución de la información", "hito_precedente": ["A8"], "subdimension": ["rh.4", "rh.5"], "subdisciplina": ["1.3"], "pregunta": "3", "dimension": ["rh"], "hito_consecuencia": ["A16"], "disciplinas": ["1"]}, {"hito_id": "A7", "fecha": 2027.5, "keywords": "", "hito_texto": "Existe un nuevo sistema de gobernanza urbana", "hito_precedente": ["A22"], "subdimension": [], "subdisciplina": ["2.3"], "pregunta": "1", "dimension": [], "hito_consecuencia": [], "disciplinas": ["2"]}, {"hito_id": "A8", "fecha": 2020.0, "keywords": "", "hito_texto": "Existe un sistema de observación y modelación urbanos coordinados, integrados y permanentes (atmosféricos, sociales, movilidad, vegetación, habitacional, etc.)", "hito_precedente": ["A20", "A21", "A23"], "subdimension": [], "subdisciplina": ["1.3"], "pregunta": "1", "dimension": [], "hito_consecuencia": ["A6"], "disciplinas": ["1"]}, {"hito_id": "A9", "fecha": 2020, "keywords": "", "hito_texto": "Se debe implementar modelos que combinen hidrodinámica y biogeoquímica de la Patagonia Chilena", "hito_precedente": ["A20", "A21"], "subdimension": ["rh.4", "rh.5"], "subdisciplina": ["1.3"], "pregunta": "3", "dimension": ["rh"], "hito_consecuencia": [], "disciplinas": ["1"]}, {"hito_id": "B1", "fecha": 2030, "keywords": "", "hito_texto": "Se regenera el corazón", "hito_precedente": [], "subdimension": [], "subdisciplina": ["1.2"], "pregunta": "", "dimension": [], "hito_consecuencia": [], "disciplinas": ["1"]}, {"hito_id": "B3", "fecha": 2024.0, "keywords": "", "hito_texto": "Se debe ver al hombre como parte de un organismo superior y no como un organismo superior en sí", "hito_precedente": [], "subdimension": [], "subdisciplina": ["2.2"], "pregunta": "", "dimension": [], "hito_consecuencia": ["B7"], "disciplinas": ["2"]}, {"hito_id": "B4", "fecha": 2040, "keywords": "", "hito_texto": "Se crea un nuevo anticancerigeno", "hito_precedente": [], "subdimension": [], "subdisciplina": ["1.2"], "pregunta": "", "dimension": [], "hito_consecuencia": ["B5"], "disciplinas": ["1"]}, {"hito_id": "B5", "fecha": 2040, "keywords": "", "hito_texto": "Chile se transforma como centro cientifico internacional", "hito_precedente": ["B4", "B8"], "subdimension": [], "subdisciplina": ["2.3"], "pregunta": "", "dimension": [], "hito_consecuencia": [], "disciplinas": ["2"]}, {"hito_id": "B6", "fecha": 2040, "keywords": "", "hito_texto": "Se debe desarrollar nuevos materiales que permitan conjugar el reciclaje y la producción energética eficiente", "hito_precedente": ["B7"], "subdimension": [], "subdisciplina": ["1.3"], "pregunta": "", "dimension": [], "hito_consecuencia": ["B8"], "disciplinas": ["1"]}, {"hito_id": "B7", "fecha": 2035, "keywords": "", "hito_texto": "Se tiene un prototipo de generación energética eficiente y sustentable", "hito_precedente": ["B3"], "subdimension": [], "subdisciplina": ["1.3"], "pregunta": "", "dimension": [], "hito_consecuencia": ["B6"], "disciplinas": ["1"]}, {"hito_id": "B8", "fecha": 2040, "keywords": "", "hito_texto": "Chile se transforma como lugar de centros internacionales de excelencia científica", "hito_precedente": ["B6"], "subdimension": [], "subdisciplina": ["2.3"], "pregunta": "", "dimension": [], "hito_consecuencia": ["B5"], "disciplinas": ["2"]}, {"hito_id": "C1", "fecha": 2018, "keywords": "", "hito_texto": "Hay formación interdisciplinaria de científicos jovenes", "hito_precedente": [], "subdimension": [], "subdisciplina": ["2.1"], "pregunta": "3", "dimension": [], "hito_consecuencia": [], "disciplinas": ["2"]}, {"hito_id": "C11", "fecha": 2027.5, "keywords": "", "hito_texto": "Existe un humano-máquina", "hito_precedente": [], "subdimension": [], "subdisciplina": ["1.3"], "pregunta": "", "dimension": [], "hito_consecuencia": [], "disciplinas": ["1"]}, {"hito_id": "C12", "fecha": 2035.0, "keywords": "", "hito_texto": "Se produce discusión ética sobre la edición genética", "hito_precedente": [], "subdimension": [], "subdisciplina": ["2.2"], "pregunta": "", "dimension": [], "hito_consecuencia": ["C7"], "disciplinas": ["2"]}, {"hito_id": "C17", "fecha": 2055.0, "keywords": "", "hito_texto": "Se producen atentados genéticos", "hito_precedente": [], "subdimension": [], "subdisciplina": ["1.2"], "pregunta": "", "dimension": [], "hito_consecuencia": [], "disciplinas": ["1"]}, {"hito_id": "C18", "fecha": 2055.0, "keywords": "", "hito_texto": "Se crea un dispositivo de vigilancia en busqueda de enfermedades para personas", "hito_precedente": ["C8"], "subdimension": [], "subdisciplina": ["1.3"], "pregunta": "", "dimension": [], "hito_consecuencia": ["C20"], "disciplinas": ["1"]}, {"hito_id": "C2", "fecha": 2025, "keywords": "", "hito_texto": "Se consolida una institucionalidad cientifica adecuada para la investigación interdisciplinar", "hito_precedente": [], "subdimension": [], "subdisciplina": ["2.3"], "pregunta": "3", "dimension": [], "hito_consecuencia": [], "disciplinas": ["2"]}, {"hito_id": "C20", "fecha": 2070, "keywords": "", "hito_texto": "Existe un hombre de 200 años", "hito_precedente": ["C18"], "subdimension": [], "subdisciplina": ["1.2"], "pregunta": "", "dimension": [], "hito_consecuencia": [], "disciplinas": ["1"]}, {"hito_id": "C3", "fecha": 2030, "keywords": "", "hito_texto": "Se identifican métodos para investigación transdisciplinar aplicables a la intersección de ciencias sociales, físicas, biológicas, técnicas, etc", "hito_precedente": [], "subdimension": [], "subdisciplina": ["2.1"], "pregunta": "3", "dimension": [], "hito_consecuencia": [], "disciplinas": ["2"]}, {"hito_id": "C4", "fecha": 2040, "keywords": "", "hito_texto": "Hay reconfiguración de análisis y teoría interdisciplinar sobre el comportamiento complejo en ámbitos técnicos", "hito_precedente": [], "subdimension": [], "subdisciplina": ["2.2"], "pregunta": "3", "dimension": [], "hito_consecuencia": [], "disciplinas": ["2"]}, {"hito_id": "C5", "fecha": 2030, "keywords": "", "hito_texto": "Se debe incorporar en el curriculum de formación docente las \"habilidades del Siglo XXI\" ", "hito_precedente": [], "subdimension": [], "subdisciplina": ["2.2"], "pregunta": "4", "dimension": [], "hito_consecuencia": [], "disciplinas": ["2"]}, {"hito_id": "C6", "fecha": 2030, "keywords": "", "hito_texto": "Se incorpora el enfoque interdisciplinario en la formación docente y las políticas educacionales", "hito_precedente": [], "subdimension": [], "subdisciplina": ["2.1"], "pregunta": "5", "dimension": [], "hito_consecuencia": [], "disciplinas": ["2"]}, {"hito_id": "C7", "fecha": 2040, "keywords": "", "hito_texto": "Se corrige el primer paciente niño con fibrosis quística", "hito_precedente": ["C12"], "subdimension": [], "subdisciplina": ["1.2"], "pregunta": "2", "dimension": [], "hito_consecuencia": [], "disciplinas": ["1"]}, {"hito_id": "C8", "fecha": 2040, "keywords": "", "hito_texto": "Se encuentra la primera señal de que una celula cualquiera va a perder el control del ciclo celular", "hito_precedente": [], "subdimension": [], "subdisciplina": ["1.3"], "pregunta": "1", "dimension": [], "hito_consecuencia": ["C18"], "disciplinas": ["1"]}, {"hito_id": "D1", "fecha": 2020, "keywords": "", "hito_texto": "Existe integración de dinámicas de pensamiento, ideas y emociones en simulaciones computacionales de sociedades humanas", "hito_precedente": ["D12"], "subdimension": [], "subdisciplina": ["3.1"], "pregunta": "1", "dimension": [], "hito_consecuencia": [], "disciplinas": ["3"]}, {"hito_id": "D10", "fecha": 2080, "keywords": "", "hito_texto": "Existen sociedades sin trabajos automatizables", "hito_precedente": [], "subdimension": [], "subdisciplina": ["2.5"], "pregunta": "2", "dimension": [], "hito_consecuencia": [], "disciplinas": ["2"]}, {"hito_id": "D12", "fecha": 2018, "keywords": "", "hito_texto": "Hay una teoría o modelo de la conciencia", "hito_precedente": [], "subdimension": [], "subdisciplina": ["2.2"], "pregunta": "", "dimension": [], "hito_consecuencia": ["D1"], "disciplinas": ["2"]}, {"hito_id": "D13", "fecha": 2025.0, "keywords": "", "hito_texto": "Existe computación neurocientífica", "hito_precedente": [], "subdimension": [], "subdisciplina": ["1.3"], "pregunta": "", "dimension": [], "hito_consecuencia": ["D3"], "disciplinas": ["1"]}, {"hito_id": "D14", "fecha": 2025.0, "keywords": "", "hito_texto": "Existe computación cuántica", "hito_precedente": [], "subdimension": [], "subdisciplina": ["1.3"], "pregunta": "", "dimension": [], "hito_consecuencia": ["D3"], "disciplinas": ["1"]}, {"hito_id": "D15", "fecha": 2045.0, "keywords": "", "hito_texto": "Se crean sociedades artificiales", "hito_precedente": ["D5"], "subdimension": [], "subdisciplina": ["1.3"], "pregunta": "", "dimension": [], "hito_consecuencia": [], "disciplinas": ["1"]}, {"hito_id": "D16", "fecha": 2045.0, "keywords": "", "hito_texto": "Aparecen dilemas éticos y políticos debido a la planificación y predicción social", "hito_precedente": ["D5", "D6"], "subdimension": [], "subdisciplina": ["2.2"], "pregunta": "", "dimension": [], "hito_consecuencia": [], "disciplinas": ["2"]}, {"hito_id": "D17", "fecha": 2045.0, "keywords": "", "hito_texto": "Hay una teoría del todo", "hito_precedente": [], "subdimension": [], "subdisciplina": ["2.2"], "pregunta": "", "dimension": [], "hito_consecuencia": [], "disciplinas": ["2"]}, {"hito_id": "D18", "fecha": 2055.0, "keywords": "", "hito_texto": "Hay transferencia de conciencia humano-máquina", "hito_precedente": ["D8"], "subdimension": [], "subdisciplina": ["3.1"], "pregunta": "", "dimension": [], "hito_consecuencia": [], "disciplinas": ["3"]}, {"hito_id": "D19", "fecha": 2055.0, "keywords": "", "hito_texto": "Existe singularidad de la conciencia artificial", "hito_precedente": ["D8"], "subdimension": [], "subdisciplina": ["3.1"], "pregunta": "", "dimension": [], "hito_consecuencia": [], "disciplinas": ["3"]}, {"hito_id": "D2", "fecha": 2030, "keywords": "", "hito_texto": "Hay educación sin orientación de mercado y sin rendición de cuentas", "hito_precedente": [], "subdimension": [], "subdisciplina": ["2.1"], "pregunta": "3", "dimension": [], "hito_consecuencia": [], "disciplinas": ["2"]}, {"hito_id": "D3", "fecha": 2035.0, "keywords": "", "hito_texto": "Las simulaciones computacionales de sociedades humanas adquieren conciencia social", "hito_precedente": ["D13", "D14"], "subdimension": [], "subdisciplina": ["2.5"], "pregunta": "1", "dimension": [], "hito_consecuencia": [], "disciplinas": ["2"]}, {"hito_id": "D4", "fecha": -1, "keywords": "", "hito_texto": "Hay libre y completo acceso a toda la información ", "hito_precedente": [], "subdimension": [], "subdisciplina": ["3.1"], "pregunta": "4", "dimension": [], "hito_consecuencia": [], "disciplinas": ["3"]}, {"hito_id": "D5", "fecha": 2040, "keywords": "", "hito_texto": "Se simulan sistemas biológicos/humanos", "hito_precedente": [], "subdimension": [], "subdisciplina": ["1.2"], "pregunta": "2", "dimension": [], "hito_consecuencia": ["D15", "D16"], "disciplinas": ["1"]}, {"hito_id": "D6", "fecha": 2040, "keywords": "", "hito_texto": "Se autoperpetúan las simulaciones computacionales humanas", "hito_precedente": [], "subdimension": [], "subdisciplina": ["1.3"], "pregunta": "1", "dimension": [], "hito_consecuencia": ["D16"], "disciplinas": ["1"]}, {"hito_id": "D8", "fecha": 2050, "keywords": "", "hito_texto": "Existe inteligencia artificial y automatización", "hito_precedente": [], "subdimension": [], "subdisciplina": ["1.3"], "pregunta": "2", "dimension": [], "hito_consecuencia": ["D18", "D19"], "disciplinas": ["1"]}, {"hito_id": "D9", "fecha": 2100, "keywords": "", "hito_texto": "La mayoría de los trabajos científicos son multidisciplinarios", "hito_precedente": [], "subdimension": [], "subdisciplina": ["2.1"], "pregunta": "2", "dimension": [], "hito_consecuencia": [], "disciplinas": ["2"]}, {"hito_id": "E1", "fecha": 2024.0, "keywords": "", "hito_texto": "Hay pensamiento computacional en colegios", "hito_precedente": ["E7"], "subdimension": [], "subdisciplina": ["1.3"], "pregunta": "2", "dimension": [], "hito_consecuencia": ["E8", "E9"], "disciplinas": ["1"]}, {"hito_id": "E10", "fecha": 2040.0, "keywords": "", "hito_texto": "Hay una crisis del sistema laborales", "hito_precedente": ["E4", "E5"], "subdimension": [], "subdisciplina": ["2.5"], "pregunta": "", "dimension": [], "hito_consecuencia": ["E11"], "disciplinas": ["2"]}, {"hito_id": "E11", "fecha": 2040.0, "keywords": "", "hito_texto": "Hay una crisis del uso de información", "hito_precedente": ["E10"], "subdimension": [], "subdisciplina": ["2.5"], "pregunta": "", "dimension": [], "hito_consecuencia": [], "disciplinas": ["2"]}, {"hito_id": "E12", "fecha": 2070, "keywords": "", "hito_texto": "hay un nuevo sistema laboral", "hito_precedente": ["E6"], "subdimension": [], "subdisciplina": ["2.5"], "pregunta": "", "dimension": [], "hito_consecuencia": [], "disciplinas": ["2"]}, {"hito_id": "E13", "fecha": 2070, "keywords": "", "hito_texto": "Se redefine el desarrollo humano", "hito_precedente": ["E6"], "subdimension": [], "subdisciplina": ["2.2"], "pregunta": "", "dimension": [], "hito_consecuencia": [], "disciplinas": ["2"]}, {"hito_id": "E2", "fecha": 2030, "keywords": "", "hito_texto": "Se crea un sistema de comunicación de datos y transmisión de larga distancia eficiente energéticamente", "hito_precedente": ["E8", "E9"], "subdimension": [], "subdisciplina": ["1.3"], "pregunta": "3", "dimension": [], "hito_consecuencia": [], "disciplinas": ["1"]}, {"hito_id": "E3", "fecha": 2030, "keywords": "", "hito_texto": "Se debe crear un sistema variable que prediga en tiempo real las enfermedades con mayor prevalencia", "hito_precedente": ["E8", "E9"], "subdimension": [], "subdisciplina": ["1.3"], "pregunta": "", "dimension": [], "hito_consecuencia": [], "disciplinas": ["1"]}, {"hito_id": "E4", "fecha": 2040, "keywords": "", "hito_texto": "Existe el primer computador cuántico personal", "hito_precedente": ["E7", "E1", "E8", "E9", "E3"], "subdimension": [], "subdisciplina": ["1.3"], "pregunta": "2", "dimension": [], "hito_consecuencia": ["E10"], "disciplinas": ["1"]}, {"hito_id": "E5", "fecha": 2040, "keywords": "", "hito_texto": "Hay diseño electrónico en los colegios", "hito_precedente": ["E7", "E1", "E8", "E9", "E2"], "subdimension": [], "subdisciplina": ["3.1"], "pregunta": "1", "dimension": [], "hito_consecuencia": ["E10"], "disciplinas": ["2"]}, {"hito_id": "E6", "fecha": 2050, "keywords": "", "hito_texto": "Hay sistemas inteligentes estandarizados en los ámbitos relevantes", "hito_precedente": ["E10", "E11"], "subdimension": [], "subdisciplina": ["1.3"], "pregunta": "1", "dimension": [], "hito_consecuencia": ["E12", "E13"], "disciplinas": ["1"]}, {"hito_id": "E7", "fecha": 2018, "keywords": "", "hito_texto": "Hay datos abiertos", "hito_precedente": [], "subdimension": [], "subdisciplina": ["1.3"], "pregunta": "", "dimension": [], "hito_consecuencia": ["E1"], "disciplinas": ["1"]}, {"hito_id": "E8", "fecha": 2024.0, "keywords": "", "hito_texto": "Hay discusión sobre regulación y ética del uso de la información", "hito_precedente": ["E1"], "subdimension": [], "subdisciplina": ["2.4"], "pregunta": "", "dimension": [], "hito_consecuencia": ["E2", "E3"], "disciplinas": ["2"]}, {"hito_id": "E9", "fecha": 2024.0, "keywords": "", "hito_texto": "Existen sensores robustos, redes estables y algoritmos eficientes", "hito_precedente": ["E1"], "subdimension": [], "subdisciplina": ["1.3"], "pregunta": "", "dimension": [], "hito_consecuencia": ["E2", "E3"], "disciplinas": ["1"]}, {"hito_id": "F1", "fecha": 2025.0, "keywords": "", "hito_texto": "Se debe llegar a las máximas profundidades del océano para realizar observaciones y recolectar muestras para su análisis en tierra", "hito_precedente": [], "subdimension": ["rh.4", "rh.5"], "subdisciplina": ["1.1"], "pregunta": "4", "dimension": ["rh"], "hito_consecuencia": [], "disciplinas": ["1"]}, {"hito_id": "F10", "fecha": 2050, "keywords": "", "hito_texto": "Hay maquinas conscientes", "hito_precedente": ["F15"], "subdimension": [], "subdisciplina": ["1.3"], "pregunta": "2", "dimension": [], "hito_consecuencia": [], "disciplinas": ["1"]}, {"hito_id": "F11", "fecha": 2055.0, "keywords": "", "hito_texto": "Hay minería espacial", "hito_precedente": [], "subdimension": [], "subdisciplina": ["1.3"], "pregunta": "3", "dimension": [], "hito_consecuencia": [], "disciplinas": ["1"]}, {"hito_id": "F12", "fecha": 2060, "keywords": "", "hito_texto": "Existe integración del conocimiento en modelos de sistema tierra", "hito_precedente": [], "subdimension": [], "subdisciplina": ["3.1"], "pregunta": "4", "dimension": [], "hito_consecuencia": [], "disciplinas": ["3"]}, {"hito_id": "F13", "fecha": 2018, "keywords": "", "hito_texto": "Hay falta de agua", "hito_precedente": [], "subdimension": ["rh.2", "rh.3"], "subdisciplina": ["1.1"], "pregunta": "", "dimension": ["rh"], "hito_consecuencia": ["F2"], "disciplinas": ["1"]}, {"hito_id": "F15", "fecha": 2040.0, "keywords": "", "hito_texto": "Se debe entender el origen de la conciencia", "hito_precedente": [], "subdimension": [], "subdisciplina": ["2.2"], "pregunta": "", "dimension": [], "hito_consecuencia": ["F10"], "disciplinas": ["2"]}, {"hito_id": "F17", "fecha": 2040, "keywords": "", "hito_texto": "Los robots interactuan con personas en el mundo real de formas diversas", "hito_precedente": ["F5"], "subdimension": [], "subdisciplina": ["2.5"], "pregunta": "", "dimension": [], "hito_consecuencia": [], "disciplinas": ["2"]}, {"hito_id": "F18", "fecha": 2035, "keywords": "", "hito_texto": "Robots cuidan personas poco valentes", "hito_precedente": [], "subdimension": [], "subdisciplina": ["2.5"], "pregunta": "", "dimension": [], "hito_consecuencia": [], "disciplinas": ["2"]}, {"hito_id": "F19", "fecha": 2040, "keywords": "", "hito_texto": "Los humanos tenemos sentimientos por las máquinas", "hito_precedente": ["F5", "F6"], "subdimension": [], "subdisciplina": ["1.3"], "pregunta": "", "dimension": [], "hito_consecuencia": [], "disciplinas": ["1"]}, {"hito_id": "F2", "fecha": 2030, "keywords": "", "hito_texto": "Se deben optimizar las operaciones auxiliares para disminuir energía, sustituir el proceso de contracción y procesar sin agua", "hito_precedente": ["F13"], "subdimension": [], "subdisciplina": ["3.1"], "pregunta": "3", "dimension": [], "hito_consecuencia": [], "disciplinas": ["3"]}, {"hito_id": "F21", "fecha": 2050, "keywords": "", "hito_texto": "Comienza la conquista por el fondo del mar", "hito_precedente": ["F8"], "subdimension": [], "subdisciplina": ["1.1"], "pregunta": "", "dimension": [], "hito_consecuencia": [], "disciplinas": ["1"]}, {"hito_id": "F5", "fecha": 2035.0, "keywords": "", "hito_texto": "Los robots pueden operar o interactuar en ambiente natural por más de 8 horas", "hito_precedente": [], "subdimension": [], "subdisciplina": ["1.3"], "pregunta": "2", "dimension": [], "hito_consecuencia": ["F17"], "disciplinas": ["1"]}, {"hito_id": "F6", "fecha": 2035.0, "keywords": "", "hito_texto": "Se deben desarrollar tecnologías que puedan trabajar a altisimas presiones con observación y experimentación in situ", "hito_precedente": [], "subdimension": [], "subdisciplina": ["1.3"], "pregunta": "4", "dimension": [], "hito_consecuencia": [], "disciplinas": ["1"]}, {"hito_id": "F7", "fecha": 2035.0, "keywords": "", "hito_texto": "Los seres humanos tenemos un dispositivio en el cuerpo desde donde somos vigilados", "hito_precedente": [], "subdimension": [], "subdisciplina": ["1.3"], "pregunta": "1", "dimension": [], "hito_consecuencia": [], "disciplinas": ["1"]}, {"hito_id": "F8", "fecha": 2040, "keywords": "", "hito_texto": "Se debe instalar un sistema de observación que permita registros continuos y sostenidos en el tiempo", "hito_precedente": [], "subdimension": [], "subdisciplina": ["1.3"], "pregunta": "4", "dimension": [], "hito_consecuencia": ["F21"], "disciplinas": ["1"]}, {"hito_id": "H1", "fecha": 2040, "keywords": "", "hito_texto": "Se reducen las inequidades en la sociedad", "hito_precedente": [], "subdimension": [], "subdisciplina": ["2.5"], "pregunta": "3", "dimension": [], "hito_consecuencia": ["H4", "H33"], "disciplinas": ["2"]}, {"hito_id": "H10", "fecha": 2055.0, "keywords": "", "hito_texto": "Se debe promover el turismo", "hito_precedente": [], "subdimension": [], "subdisciplina": ["2.5"], "pregunta": "", "dimension": [], "hito_consecuencia": ["H13"], "disciplinas": ["2"]}, {"hito_id": "H11", "fecha": 2055.0, "keywords": "", "hito_texto": "Hay tratamientos en salud mejores y mas efectivos", "hito_precedente": ["H2"], "subdimension": [], "subdisciplina": ["2.5"], "pregunta": "", "dimension": [], "hito_consecuencia": ["H12"], "disciplinas": ["2"]}, {"hito_id": "H12", "fecha": 2060, "keywords": "", "hito_texto": "Hay mayor expectativa de vida y en mejores condiciones", "hito_precedente": ["H8", "H11"], "subdimension": [], "subdisciplina": ["2.5"], "pregunta": "", "dimension": [], "hito_consecuencia": ["H17"], "disciplinas": ["2"]}, {"hito_id": "H13", "fecha": 2060, "keywords": "", "hito_texto": "Se debe conocer como reconstruir los ecosistemas", "hito_precedente": ["H10"], "subdimension": [], "subdisciplina": ["1.1"], "pregunta": "", "dimension": [], "hito_consecuencia": ["H17"], "disciplinas": ["1"]}, {"hito_id": "H14", "fecha": 2055.0, "keywords": "", "hito_texto": "Se deben generar estrategias para minimizar los impactos socio-económicos", "hito_precedente": ["H9"], "subdimension": [], "subdisciplina": ["3.1"], "pregunta": "", "dimension": [], "hito_consecuencia": ["H16"], "disciplinas": ["3"]}, {"hito_id": "H15", "fecha": 2060, "keywords": "", "hito_texto": "Se mejoran los servicios básicos", "hito_precedente": [], "subdimension": [], "subdisciplina": ["2.3"], "pregunta": "", "dimension": [], "hito_consecuencia": ["H17"], "disciplinas": ["2"]}, {"hito_id": "H16", "fecha": 2060, "keywords": "", "hito_texto": "Se debe diversificar el uso de recursos", "hito_precedente": ["H14"], "subdimension": ["rh.3"], "subdisciplina": ["3.1"], "pregunta": "", "dimension": ["rh"], "hito_consecuencia": ["H17"], "disciplinas": ["3"]}, {"hito_id": "H17", "fecha": 2070, "keywords": "", "hito_texto": "Hay mayor y mejor integración de la sociedad y paz social", "hito_precedente": ["H12", "H13", "H15", "H16"], "subdimension": [], "subdisciplina": ["2.5"], "pregunta": "", "dimension": [], "hito_consecuencia": [], "disciplinas": ["2"]}, {"hito_id": "H2", "fecha": 2045.0, "keywords": "", "hito_texto": "Mejora la calidad de vida de la persona", "hito_precedente": ["H4", "H33"], "subdimension": [], "subdisciplina": ["2.5"], "pregunta": "", "dimension": [], "hito_consecuencia": ["H7", "H11"], "disciplinas": ["2"]}, {"hito_id": "H20", "fecha": 2050, "keywords": "", "hito_texto": "Existen nuevas formas de comprender", "hito_precedente": ["H5"], "subdimension": [], "subdisciplina": ["2.2"], "pregunta": "", "dimension": [], "hito_consecuencia": [], "disciplinas": ["2"]}, {"hito_id": "H25", "fecha": 2018, "keywords": "", "hito_texto": "Se debe mejorar la comunicación de la ciencia y la vigencia de los problemas", "hito_precedente": [], "subdimension": [], "subdisciplina": ["2.5"], "pregunta": "2", "dimension": [], "hito_consecuencia": [], "disciplinas": ["2"]}, {"hito_id": "H29", "fecha": 2024.0, "keywords": "", "hito_texto": "Se debe comprender la respuesta de los elementos naturales y sociales frente a forzantes de cambio", "hito_precedente": [], "subdimension": [], "subdisciplina": ["2.5"], "pregunta": "1", "dimension": [], "hito_consecuencia": [], "disciplinas": ["2"]}, {"hito_id": "H3", "fecha": 2045.0, "keywords": "", "hito_texto": "Hay nuevas formas de gobierno", "hito_precedente": [], "subdimension": [], "subdisciplina": ["2.3"], "pregunta": "", "dimension": [], "hito_consecuencia": [], "disciplinas": ["2"]}, {"hito_id": "H4", "fecha": 2040, "keywords": "", "hito_texto": "Mejora el uso de los recursos del país", "hito_precedente": ["H1"], "subdimension": ["rh.3"], "subdisciplina": ["2.3"], "pregunta": "2", "dimension": ["rh"], "hito_consecuencia": ["H2", "H8"], "disciplinas": ["2"]}, {"hito_id": "H33", "fecha": 2040, "keywords": "", "hito_texto": "Se reducen los desastres ambientales", "hito_precedente": [], "subdimension": [], "subdisciplina": ["1.1"], "pregunta": "2", "dimension": [], "hito_consecuencia": ["H20"], "disciplinas": ["1"]}, {"hito_id": "H5", "fecha": 2040, "keywords": "", "hito_texto": "Se deben priorizar acciones transversales entre los ministerios", "hito_precedente": ["H7"], "subdimension": [], "subdisciplina": ["2.3"], "pregunta": "1", "dimension": [], "hito_consecuencia": [], "disciplinas": ["2"]}, {"hito_id": "H6", "fecha": 2045.0, "keywords": "", "hito_texto": "Se debe potenciar el arte", "hito_precedente": ["H2"], "subdimension": [], "subdisciplina": ["2.5"], "pregunta": "", "dimension": [], "hito_consecuencia": ["H6"], "disciplinas": ["2"]}, {"hito_id": "H7", "fecha": 2045.0, "keywords": "", "hito_texto": "Se debe mejorar la valorización de la biodiversidad y del capital verde del país", "hito_precedente": ["H4", "H33"], "subdimension": [], "subdisciplina": ["2.5"], "pregunta": "", "dimension": [], "hito_consecuencia": ["H12"], "disciplinas": ["2"]}, {"hito_id": "H8", "fecha": 2050, "keywords": "", "hito_texto": "Se cambia a una economía basada en energías limpias", "hito_precedente": [], "subdimension": [], "subdisciplina": ["2.4"], "pregunta": "", "dimension": [], "hito_consecuencia": ["H14"], "disciplinas": ["2"]}, {"hito_id": "H9", "fecha": 2050, "keywords": "", "hito_texto": "Se deben generar herramientas para lograr capacidad adaptativa", "hito_precedente": [], "subdimension": [], "subdisciplina": ["3.1"], "pregunta": "", "dimension": [], "hito_consecuencia": [], "disciplinas": ["3"]}]